{
    "points": [
        [
            -182,
            -71
        ],
        [
            182,
            -70
        ],
        [
            -183,
            -69
        ],
        [
            182,
            -69
        ],
        [
            -184,
            -68
        ],
        [
            183,
            -68
        ],
        [
            -184,
            -67
        ],
        [
            183,
            -67
        ],
        [
            -184,
            -66
        ],
        [
            183,
            -66
        ],
        [
            -185,
            -65
        ],
        [
            183,
            -65
        ],
        [
            -185,
            -64
        ],
        [
            184,
            -64
        ],
        [
            -186,
            -63
        ],
        [
            184,
            -63
        ],
        [
            -186,
            -62
        ],
        [
            184,
            -62
        ],
        [
            -186,
            -61
        ],
        [
            184,
            -61
        ],
        [
            -187,
            -60
        ],
        [
            185,
            -60
        ],
        [
            -187,
            -59
        ],
        [
            185,
            -59
        ],
        [
            -188,
            -58
        ],
        [
            185,
            -58
        ],
        [
            -188,
            -57
        ],
        [
            185,
            -57
        ],
        [
            -189,
            -56
        ],
        [
            186,
            -56
        ],
        [
            -189,
            -55
        ],
        [
            186,
            -55
        ],
        [
            -189,
            -54
        ],
        [
            186,
            -54
        ],
        [
            -190,
            -53
        ],
        [
            186,
            -53
        ],
        [
            -191,
            -51
        ],
        [
            187,
            -51
        ],
        [
            -191,
            -50
        ],
        [
            187,
            -50
        ],
        [
            -192,
            -49
        ],
        [
            187,
            -49
        ],
        [
            -192,
            -48
        ],
        [
            187,
            -48
        ],
        [
            -192,
            -47
        ],
        [
            188,
            -47
        ],
        [
            -193,
            -46
        ],
        [
            188,
            -46
        ],
        [
            -193,
            -45
        ],
        [
            188,
            -45
        ],
        [
            -194,
            -44
        ],
        [
            188,
            -44
        ],
        [
            -194,
            -43
        ],
        [
            189,
            -43
        ],
        [
            -195,
            -42
        ],
        [
            189,
            -42
        ],
        [
            -195,
            -41
        ],
        [
            189,
            -41
        ],
        [
            -195,
            -40
        ],
        [
            189,
            -40
        ],
        [
            -193,
            -39
        ],
        [
            190,
            -39
        ]
    ],
    "anchor": "bottom_center",
    "original_anchor": [
        240,
        270
    ],
    "original_dimensions": [
        480,
        270
    ],
    "type": "mask"
}