{
  "points": [
    [
      -122,
      -99
    ],
    [
      -22,
      -99
    ],
    [
      -168,
      -94
    ],
    [
      -2,
      -94
    ],
    [
      -188,
      -89
    ],
    [
      8,
      -89
    ],
    [
      -198,
      -84
    ],
    [
      123,
      -84
    ],
    [
      -203,
      -79
    ],
    [
      133,
      -79
    ],
    [
      -208,
      -74
    ],
    [
      138,
      -74
    ],
    [
      -213,
      -69
    ],
    [
      143,
      -69
    ],
    [
      -218,
      -64
    ],
    [
      148,
      -64
    ],
    [
      -218,
      -59
    ],
    [
      154,
      -59
    ],
    [
      -223,
      -54
    ],
    [
      154,
      -54
    ],
    [
      -223,
      -49
    ],
    [
      159,
      -49
    ],
    [
      -223,
      -44
    ],
    [
      159,
      -44
    ],
    [
      -223,
      -39
    ],
    [
      159,
      -39
    ],
    [
      -223,
      -34
    ],
    [
      159,
      -34
    ],
    [
      -223,
      -29
    ],
    [
      159,
      -29
    ],
    [
      -223,
      -24
    ],
    [
      159,
      -24
    ],
    [
      -218,
      -19
    ],
    [
      159,
      -19
    ],
    [
      -218,
      -14
    ],
    [
      159,
      -14
    ],
    [
      -213,
      -9
    ],
    [
      159,
      -9
    ],
    [
      -208,
      -4
    ],
    [
      159,
      -4
    ]
  ],
  "anchor": "bottom_center",
  "anchor_point_in_image": [
    228,
    1056
  ],
  "original_dimensions": [
    458,
    1057
  ],
  "type": "draw"
}